{
  "project_info": {
    "project_id": "eps-medical",
    "project_number": "262070217505",
    "name": "EPS Medical"
  },
  "client": [
    {
      "client_info": {
        "mobilesdk_app_id": "1:262070217505:android:9e4273a46bca657c",
        "client_id": "android:com.zetsuei.epsmedical.app",
        "client_type": 1,
        "android_client_info": {
          "package_name": "com.zetsuei.epsmedical.app"
        }
      },
      "oauth_client": [],
      "api_key": [],
      "services": {
        "analytics_service": {
          "status": 2,
          "analytics_property": {
            "tracking_id": "UA-49937164-1"
          }
        },
        "cloud_messaging_service": {
          "status": 1,
          "apns_config": []
        },
        "appinvite_service": {
          "status": 1,
          "other_platform_oauth_client": []
        },
        "google_signin_service": {
          "status": 1
        },
        "ads_service": {
          "status": 1
        }
      }
    }
  ],
  "client_info": [],
  "ARTIFACT_VERSION": "1"
}